<?xml version="1.0" encoding="UTF-8"?>
<metadata xmlns:xsi="http://www.w3.org/2001/XMLSchema-instance" xmlns:dc="http://purl.org/dc/elements/1.1/" xmlns:dcterms="http://purl.org/dc/terms/">
	<collection xml:id="Museo Virtuale delle Vite Vasariane">
		<item n="3.1.2" xml:id="ITEM">
			<dc:title xsi:type="mp:GND" mp:ref="http://d-nb.info/gnd/4432505-8">Battesimo di Cristo</dc:title>
			<dc:creator xsi:type="mp:ULAN" mp:ref="http://vocab.getty.edu/page/ulan/500003951">Andrea del Verrocchio</dc:creator>
			<dc:creator xsi:type="mp:ULAN" mp:ref="http://vocab.getty.edu/page/ulan/500010879">Leonardo da Vinci</dc:creator>
			<dc:date>1472-1475</dc:date>

			<dc:subject xml:lang="it">arte, arti figurative, dipinto, olio e tempera su tavola</dc:subject>
			<dc:subject xsi:type="dcterms:UDC">75</dc:subject>
			<dc:subject xml:lang="it">Rinascimento</dc:subject>
			<dc:subject xsi:type="dcterms:UDC">7.034</dc:subject>

			<dc:description>Sulle rive del fiume Giordano, in Palestina, Gesù riceve il sacramento del battesimo da san Giovanni, che gli terge la testa versando dell’acqua</dc:description>

			<dc:type>immagine</dc:type>
			<dc:format xsi:type="dcterms:IMT">image/jp2</dc:format>
			<dc:format>177*151 cm</dc:format>
			<dc:identifier xsi:type="dcterms:URI">https://github.com/elisaporcaro/progetto-esame/blob/cdb2a90436a19351d4e61ef642844e9c47532f29/img/battesimo.jpg</dc:identifier>
			<dc:coverage xsi:type="mp:CONA" mp:ref="http://vocab.getty.edu/page/cona/700009652">Museo degli Uffizi</dc:coverage>
			<dc:coverage xsi:type="mp:TGN" mp:ref="http://vocab.getty.edu/page/tgn/7003163">Firenze</dc:coverage>
		</item>
	</collection>
</metadata>