<?xml version="1.0" encoding="UTF-8"?>
<library
	xmlns:xsi="http://www.w3.org/2001/XMLSchema-instance"
	xmlns:dc="http://purl.org/dc/elements/1.1/"
	xmlns="http://www.iccu.sbn.it/metaAG1.pdf"
	xsi:schemaLocation="http://www.iccu.sbn.it/metaAG1.pdf metadigit.xsd"
	version="2.0"
	xml:id="BIBIT">

	<author xml:id="v07">
		<text xml:id="v07-0301">
			<dc:identifier xsi:type="SBN">IT\ICCU\CFI\0114559</dc:identifier>
			<dc:title>Leonardo da Vinci, pittore e scultore fiorentino</dc:title>
			<dc:creator>Vasari, Giorgio</dc:creator>
			<dc:date>2004</dc:date>
			<dc:subject>709.45 - Storia dell'arte. Italia.</dc:subject>
			<dc:subject>Memorialistica</dc:subject>
			<dc:subject>500</dc:subject>
			<dc:description>capitolo tratto dal testo di Giorgio Vasari "Le Vite de' più eccellenti architetti, pittori, et scultori italiani, da Cimabue insino a' tempi nostri : nell'edizione per i tipi di Lorenzo Torrentino, Firenze 1550 - Torino: G. Einaudi, 1986" dedicato a Leonardo da Vinci</dc:description>
			<dc:publisher>Roma : Biblioteca Italiana</dc:publisher>
			<dc:format>electronic - 1746016</dc:format>
			<dc:identifier> IT\ICCU\CFI\0114559</dc:identifier>
			<dc:language>ita</dc:language>
			<dc:language>lat</dc:language>
			<dc:source xsi:type="dcterms:URI">http://www.bibliotecaitaliana.it/testo/bibit001650</dc:source>
			<dc:rights>Accesso libero per uso personale o scientifico. Ogni uso commercile è vietato</dc:rights>
			<dc:type>text</dc:type>
		</text>
	</author>
</library>